adrianna/__init__.py
adrianna-0.0.7.2.dist-info/LICENSE
adrianna-0.0.7.2.dist-info/METADATA
adrianna-0.0.7.2.dist-info/WHEEL
adrianna-0.0.7.2.dist-info/top_level.txt
adrianna-0.0.7.2.dist-info/RECORD
