Metadata-Version: 2.1
Name: adrianna
Version: 0.0.7.2
Summary: lib for development with machine learning
Home-page: https://github.com/reinanbr/adriana
Author: Reinan Br
Author-email: slimchatuba@gmail.com
License: MIT License
Keywords: ia machine learning math
License-File: LICENSE
Requires-Dist: numpy
Requires-Dist: scipy
